cft_zarr/__init__.py
cft_zarr/chunked_jpeg.py
cft_zarr/jpeg.py
cft_zarr/jpeg_compressor.py
cft_zarr/jpegxl.py
cft_zarr/napari.yaml
cft_zarr/shift12jls.py
cft_zarr/shift12jls_compressor.py
cft_zarr-0.0.6.dist-info/METADATA
cft_zarr-0.0.6.dist-info/WHEEL
cft_zarr-0.0.6.dist-info/entry_points.txt
cft_zarr-0.0.6.dist-info/RECORD
