Metadata-Version: 2.3
Name: cft-zarr
Version: 0.0.6
Summary: CFT Zarr codecs for 12-bit fluorescence and RGB compression
Author: Eli White
Author-email: eliwhite@gmail.com
Requires-Python: >=3.11,<=3.14
Classifier: Programming Language :: Python :: 3
Classifier: Programming Language :: Python :: 3.11
Classifier: Programming Language :: Python :: 3.12
Classifier: Programming Language :: Python :: 3.13
Requires-Dist: imagecodecs (>=2024.1.1)
Requires-Dist: numpy (>=2.0.0,<3.0.0)
Requires-Dist: zarr (>=3.0.0)
